xytb/__init__.py
xytb/cli.py
xytb/py.typed
xytb/apps/__init__.py
xytb/apps/codereview.py
xytb/crawl/weixin.py
xytb/tmux/__init__.py
xytb-1.7.0.dist-info/METADATA
xytb-1.7.0.dist-info/WHEEL
xytb-1.7.0.dist-info/entry_points.txt
xytb-1.7.0.dist-info/top_level.txt
xytb-1.7.0.dist-info/RECORD
