Metadata-Version: 2.4
Name: xytb
Version: 1.7.0
Summary: xytb is just (x)iao (y)ang's (t)ool(b)ox; https://github.com/you-n-g/toolbox
Author-email: Young <afe.young@gmail.com>
Project-URL: Repository, https://github.com/you-n-g/toolbox
Requires-Python: >=3.10
Requires-Dist: libtmux>=0.47.0
Requires-Dist: litellm>=1.73.2
Requires-Dist: loguru>=0.7.3
Requires-Dist: pydantic-settings>=2.10.1
Requires-Dist: rich>=14.0.0
Requires-Dist: typer>=0.16.0
Provides-Extra: crawl
Requires-Dist: selenium>=4.27.1; extra == "crawl"
Provides-Extra: dev
Requires-Dist: pytest; extra == "dev"
